agent.py
agent_http_org.py
blackboard_grpc_client.py
blackboard_http_client.py
builder.py
default_args.py
enums.py
promise_set.py
test.py
types_pb2.py
types_pb2_grpc.py
smcore_beta-0.0.20.dist-info/LICENSE
smcore_beta-0.0.20.dist-info/METADATA
smcore_beta-0.0.20.dist-info/WHEEL
smcore_beta-0.0.20.dist-info/top_level.txt
smcore_beta-0.0.20.dist-info/RECORD
