Metadata-Version: 2.1
Name: smcore-beta
Version: 0.0.20
Summary: Package providing base sm agent classes and clients
Author-email: "J. Hoffman, J. Genender" <johnmarianhoffman@gmail.com>
Project-URL: Homepage, https://gitlab.com/sm-ai-team/sm-core-go
Project-URL: Bug Tracker, https://gitlab.com/sm-ai-team/sm-core-go/issues
Classifier: Programming Language :: Python :: 3
Classifier: License :: OSI Approved :: BSD License
Classifier: Operating System :: OS Independent
Requires-Python: >=3.10
License-File: LICENSE
Requires-Dist: requests ==2.31.0
Requires-Dist: protobuf ==4.21.12
